likhil/__init__.py
likhil/nameprint.py
likhil/version.py
likhil-0.0.1.dist-info/LICENSE.txt
likhil-0.0.1.dist-info/METADATA
likhil-0.0.1.dist-info/WHEEL
likhil-0.0.1.dist-info/top_level.txt
likhil-0.0.1.dist-info/RECORD
